vizflow/__init__.py
vizflow/config.py
vizflow/io.py
vizflow/market.py
vizflow/ops.py
vizflow/py.typed
vizflow/schema_evolution.py
vizflow/viz.py
vizflow-0.5.9.dist-info/METADATA
vizflow-0.5.9.dist-info/WHEEL
vizflow-0.5.9.dist-info/RECORD
