Metadata-Version: 2.4
Name: vizflow
Version: 0.5.9
Requires-Python: >=3.9
Requires-Dist: polars>=0.20.0
Provides-Extra: dev
Requires-Dist: build; extra == 'dev'
Requires-Dist: pytest>=7.0; extra == 'dev'
Requires-Dist: ruff>=0.1.0; extra == 'dev'
Requires-Dist: twine; extra == 'dev'
Provides-Extra: viz
Requires-Dist: dash>=2.0; extra == 'viz'
Requires-Dist: plotly>=5.0; extra == 'viz'
